MANIFEST.in
README.md
setup.py
docs/collaboration.rst
docs/extending.rst
docs/index.rst
docs/installation.rst
docs/irl_benchmark.config.rst
docs/irl_benchmark.experiment.rst
docs/irl_benchmark.irl.algorithms.rst
docs/irl_benchmark.irl.collect.rst
docs/irl_benchmark.irl.feature.rst
docs/irl_benchmark.irl.reward.rst
docs/irl_benchmark.irl.rst
docs/irl_benchmark.metrics.rst
docs/irl_benchmark.rl.algorithms.rst
docs/irl_benchmark.rl.rst
docs/irl_benchmark.rst
docs/irl_benchmark.utils.rst
docs/modules.rst
docs/quickstart.rst
irl_benchmark/__init__.py
irl_benchmark.egg-info/PKG-INFO
irl_benchmark.egg-info/SOURCES.txt
irl_benchmark.egg-info/dependency_links.txt
irl_benchmark.egg-info/requires.txt
irl_benchmark.egg-info/top_level.txt
irl_benchmark/config/__init__.py
irl_benchmark/experiment/__init__.py
irl_benchmark/experiment/run.py
irl_benchmark/irl/__init__.py
irl_benchmark/irl/algorithms/__init__.py
irl_benchmark/irl/algorithms/appr_irl.py
irl_benchmark/irl/algorithms/base_algorithm.py
irl_benchmark/irl/algorithms/mce_irl.py
irl_benchmark/irl/algorithms/me_irl.py
irl_benchmark/irl/collect/__init__.py
irl_benchmark/irl/feature/__init__.py
irl_benchmark/irl/feature/feature_wrapper.py
irl_benchmark/irl/reward/__init__.py
irl_benchmark/irl/reward/reward_function.py
irl_benchmark/irl/reward/reward_wrapper.py
irl_benchmark/irl/reward/truth.py
irl_benchmark/metrics/__init__.py
irl_benchmark/metrics/avg_traj_return.py
irl_benchmark/metrics/base_metric.py
irl_benchmark/metrics/feature_count_inf.py
irl_benchmark/metrics/feature_count_l2.py
irl_benchmark/rl/__init__.py
irl_benchmark/rl/algorithms/__init__.py
irl_benchmark/rl/algorithms/base_algorithm.py
irl_benchmark/rl/algorithms/random_agent.py
irl_benchmark/rl/algorithms/value_iteration.py
irl_benchmark/utils/__init__.py
irl_benchmark/utils/general.py
irl_benchmark/utils/irl.py
irl_benchmark/utils/rl.py
irl_benchmark/utils/wrapper.py