Metadata-Version: 1.0
Name: irl-benchmark
Version: 0.1.0
Summary: Benchmark framework for inverse reinforcement learning algorithms.
Home-page: https://github.com/JohannesHeidecke/irl-benchmark
Author: Anton Osika, Adria Garriga-Alonso, Johannes Heidecke, Max Daniel, Sayan Sarkar
Author-email: jheidecke@gmail.com
License: LICENSE
Platform: UNKNOWN
